LICENSE
README.md
setup.py
nerpy/__init__.py
nerpy/bertspan.py
nerpy/dataset.py
nerpy/get_file.py
nerpy/losses.py
nerpy/model_args.py
nerpy/ner_model.py
nerpy/ner_utils.py
nerpy/version.py
nerpy.egg-info/PKG-INFO
nerpy.egg-info/SOURCES.txt
nerpy.egg-info/dependency_links.txt
nerpy.egg-info/not-zip-safe
nerpy.egg-info/requires.txt
nerpy.egg-info/top_level.txt