Metadata-Version: 2.1
Name: nerpy
Version: 0.1.2
Summary: nerpy: Named Entity Recognition toolkit using Python
Home-page: https://github.com/shibing624/nerpy
Author: XuMing
Author-email: xuming624@qq.com
License: Apache License 2.0
Keywords: NER,nerpy,Chinese Named Entity Recognition Tool,ner,bert,bert2tag
Platform: UNKNOWN
Classifier: Development Status :: 5 - Production/Stable
Classifier: Intended Audience :: Developers
Classifier: Intended Audience :: Education
Classifier: Intended Audience :: Science/Research
Classifier: License :: OSI Approved :: Apache Software License
Classifier: Operating System :: OS Independent
Classifier: Programming Language :: Python :: 3
Classifier: Programming Language :: Python :: 3.8
Classifier: Programming Language :: Python :: 3.9
Classifier: Topic :: Scientific/Engineering :: Artificial Intelligence
Requires-Python: >=3.8
License-File: LICENSE
